<metadata xml:lang="ru"><Esri><CreaDate>20220313</CreaDate><CreaTime>09282600</CreaTime><ArcGISFormat>1.0</ArcGISFormat><SyncOnce>TRUE</SyncOnce><ModDate>20220320</ModDate><ModTime>10211700</ModTime><scaleRange><minScale>150000000</minScale><maxScale>5000</maxScale></scaleRange><ArcGISProfile>ItemDescription</ArcGISProfile></Esri><tool name="XYtoPolygon" displayname="Создание полигонов из таблицы Excel XY (таблица -&gt; полигон)" toolboxalias="" xmlns=""><arcToolboxHelpPath>c:\program files (x86)\arcgis\desktop10.8\Help\gp</arcToolboxHelpPath><parameters><param name="in_excel_file" displayname="Входной Excel-файл с координатами XY" type="Required" direction="Input" datatype="Файл" expression="in_excel_file"><dialogReference>&lt;DIV STYLE="text-align:Left;"&gt;&lt;DIV&gt;&lt;P&gt;&lt;SPAN&gt;Входной файл &lt;/SPAN&gt;&lt;SPAN&gt;Excel (.xls, .xlsx)&lt;/SPAN&gt;&lt;/P&gt;&lt;/DIV&gt;&lt;/DIV&gt;</dialogReference></param><param name="in_x_coord" displayname="Поле X" type="Required" direction="Input" datatype="Строка" expression="in_x_coord"><dialogReference>&lt;DIV STYLE="text-align:Left;"&gt;&lt;DIV&gt;&lt;P&gt;&lt;SPAN&gt;Входная координата &lt;/SPAN&gt;&lt;SPAN&gt;X&lt;/SPAN&gt;&lt;/P&gt;&lt;/DIV&gt;&lt;/DIV&gt;</dialogReference></param><param name="in_y_coord" displayname="Поле Y" type="Required" direction="Input" datatype="Строка" expression="in_y_coord"><dialogReference>&lt;DIV STYLE="text-align:Left;"&gt;&lt;DIV&gt;&lt;P&gt;&lt;SPAN&gt;Входная координата &lt;/SPAN&gt;&lt;SPAN&gt;Y&lt;/SPAN&gt;&lt;/P&gt;&lt;/DIV&gt;&lt;/DIV&gt;</dialogReference></param><param name="in_line_field_opt" displayname="Сформировать полигоны по значению" type="Optional" direction="Input" datatype="Строка" expression="{in_line_field_opt}"><dialogReference>&lt;DIV STYLE="text-align:Left;"&gt;&lt;DIV&gt;&lt;P&gt;&lt;SPAN&gt;Поле-разделитель полигонов&lt;/SPAN&gt;&lt;/P&gt;&lt;/DIV&gt;&lt;/DIV&gt;</dialogReference></param><param name=" in_line_close_opt" displayname="Замкнуть координаты" type="Optional" direction="Input" datatype="Булевы операторы" expression="{ in_line_close_opt}"><dialogReference>&lt;DIV STYLE="text-align:Left;"&gt;&lt;DIV&gt;&lt;P&gt;&lt;SPAN&gt;Замкнуть линию&lt;/SPAN&gt;&lt;/P&gt;&lt;/DIV&gt;&lt;/DIV&gt;</dialogReference></param><param name="in_cs" displayname="Система координат входных данных" type="Required" direction="Input" datatype="Система координат" expression="in_cs"><dialogReference>&lt;DIV STYLE="text-align:Left;"&gt;&lt;DIV&gt;&lt;P&gt;&lt;SPAN&gt;Входная система координат&lt;/SPAN&gt;&lt;/P&gt;&lt;/DIV&gt;&lt;/DIV&gt;</dialogReference></param><param name="in_GDB_opt" displayname="Выходная база геоданных" type="Optional" direction="Input" datatype="Рабочая область" expression="{in_GDB_opt}"><dialogReference>&lt;DIV STYLE="text-align:Left;"&gt;&lt;DIV&gt;&lt;P&gt;&lt;SPAN&gt;Выходная база геоданных&lt;/SPAN&gt;&lt;/P&gt;&lt;/DIV&gt;&lt;/DIV&gt;</dialogReference></param></parameters><summary>&lt;DIV STYLE="text-align:Left;"&gt;&lt;DIV&gt;&lt;P&gt;&lt;SPAN&gt;Строит полигональные объекты из таблиц &lt;/SPAN&gt;&lt;SPAN&gt;Excel (.xls, xlsx)&lt;/SPAN&gt;&lt;/P&gt;&lt;/DIV&gt;&lt;/DIV&gt;</summary></tool><dataIdInfo><idCitation><resTitle>Создание полигонов из таблицы Excel XY (таблица -&gt; полигон)</resTitle></idCitation><idAbs>&lt;DIV STYLE="text-align:Left;"&gt;&lt;DIV&gt;&lt;P&gt;&lt;SPAN&gt;Строит полигональные объекты из таблиц &lt;/SPAN&gt;&lt;SPAN&gt;Excel (.xls, xlsx)&lt;/SPAN&gt;&lt;/P&gt;&lt;/DIV&gt;&lt;/DIV&gt;</idAbs><idCredit>КУ НАО "НИАЦ" - Льдоков Д.В.</idCredit><searchKeys><keyword>XY</keyword><keyword>полигоны</keyword></searchKeys></dataIdInfo><distInfo><distributor><distorFormat><formatName>ArcToolbox Tool</formatName></distorFormat></distributor></distInfo><mdHrLv><ScopeCd value="005"></ScopeCd></mdHrLv></metadata>
